setup.cfg
setup.py
ValleyBackups.egg-info/PKG-INFO
ValleyBackups.egg-info/SOURCES.txt
ValleyBackups.egg-info/dependency_links.txt
ValleyBackups.egg-info/entry_points.txt
ValleyBackups.egg-info/requires.txt
ValleyBackups.egg-info/top_level.txt
valleybackups/__init__.py
valleybackups/cli.py
valleybackups/config_context.py
valleybackups/config_handler.py
valleybackups/db.py
valleybackups/exceptions.py
valleybackups/server.py
valleybackups/test.py
valleybackups/util.py
valleybackups.egg-info/SOURCES.txt
valleybackups/commands/__init__.py
valleybackups/commands/cmd_backup.py
valleybackups/commands/cmd_batch_upload.py
valleybackups/commands/cmd_check_config.py
valleybackups/commands/cmd_create_vault.py
valleybackups/commands/cmd_download.py
valleybackups/commands/cmd_get_config.py
valleybackups/commands/cmd_list.py
valleybackups/commands/cmd_list_uncompleted_jobs.py
valleybackups/commands/cmd_request.py
valleybackups/commands/cmd_set_config.py
valleybackups/commands/cmd_start_sns_listener.py
valleybackups/extensions/__init__.py
valleybackups/extensions/glacier.py