Metadata-Version: 1.1
Name: valleybackups
Version: 0.1.17
Summary: Command-line based AWS Glacier backup tool
Home-page: http://www.valleyworks.us
Author: Valley Works
Author-email: valleybackups@valleyworks.us
License: MIT
Keywords: backup glacier aws
Platform: UNKNOWN
Classifier: Development Status :: 4 - Beta
Classifier: License :: OSI Approved :: MIT License
Classifier: Programming Language :: Python :: 2.7
